cmd_window/__init__.py
cmd_window/cmd_window.py
cmd_window/window.py
cmd_window-0.3.3.dist-info/licenses/LICENSE
cmd_window-0.3.3.dist-info/METADATA
cmd_window-0.3.3.dist-info/WHEEL
cmd_window-0.3.3.dist-info/top_level.txt
cmd_window-0.3.3.dist-info/RECORD
