Metadata-Version: 2.4
Name: cmd_window
Version: 0.3.3
Summary: This python module makes it easy to create text-based, graphical interfaces.
Home-page: https://github.com/peterczegledy/Python-modules/tree/main/cmd_window
Author: Czeglédy Péter
Author-email: czegledyp2@gmail.com
License: MIT
Classifier: Programming Language :: Python :: 3
Classifier: Operating System :: OS Independent
Requires-Python: >=3.6
License-File: LICENSE
Requires-Dist: pynput
Requires-Dist: windows-curses
Dynamic: author
Dynamic: author-email
Dynamic: classifier
Dynamic: description
Dynamic: description-content-type
Dynamic: home-page
Dynamic: license
Dynamic: license-file
Dynamic: requires-dist
Dynamic: requires-python
Dynamic: summary
